json_logic_asp/__init__.py
json_logic_asp/adapters/__init__.py
json_logic_asp/adapters/asp/__init__.py
json_logic_asp/adapters/asp/asp_literals.py
json_logic_asp/adapters/asp/asp_statements.py
json_logic_asp/adapters/json_logic/__init__.py
json_logic_asp/adapters/json_logic/jl_array_nodes.py
json_logic_asp/adapters/json_logic/jl_boolean_nodes.py
json_logic_asp/adapters/json_logic/jl_data_nodes.py
json_logic_asp/adapters/json_logic/jl_helper_nodes.py
json_logic_asp/adapters/json_logic/jl_logic_nodes.py
json_logic_asp/constants/__init__.py
json_logic_asp/constants/asp_naming.py
json_logic_asp/constants/json_logic_ops.py
json_logic_asp/constants/loggers.py
json_logic_asp/evaluator.py
json_logic_asp/invoker/__init__.py
json_logic_asp/invoker/run.py
json_logic_asp/models/__init__.py
json_logic_asp/models/asp_base.py
json_logic_asp/models/clingo_dto.py
json_logic_asp/models/json_logic_nodes.py
json_logic_asp/models/translator_dto.py
json_logic_asp/py.typed
json_logic_asp/sdk/__init__.py
json_logic_asp/sdk/clingo_sdk.py
json_logic_asp/simplifier/__init__.py
json_logic_asp/simplifier/node_simplifier.py
json_logic_asp/simplifier/simplify.py
json_logic_asp/translator/__init__.py
json_logic_asp/translator/data_generator.py
json_logic_asp/translator/eval_translator.py
json_logic_asp/translator/rule_generator.py
json_logic_asp/utils/__init__.py
json_logic_asp/utils/id_management.py
json_logic_asp/utils/json_logic_helpers.py
json_logic_asp/utils/list_utils.py
json_logic_asp-0.3.2.dist-info/LICENSE
json_logic_asp-0.3.2.dist-info/METADATA
json_logic_asp-0.3.2.dist-info/WHEEL
json_logic_asp-0.3.2.dist-info/RECORD
